{
  "dropCollections": true,
  "public": {
    "clientOnly": true,
    "verifyEmail": false,
    "ui": {
        "studyListFunctionsEnabled": true,
        "leftSidebarOpen": false,
        "displaySetNavigationLoopOverSeries": false,
        "displaySetNavigationMultipleViewports": true,
        "autoPositionMeasurementsTextCallOuts": "TRLB",
        "studyListDateFilterNumDays": 1
    },
    "servers": {
      "dicomWeb": [
        {
          "name": "Orthanc",
          "wadoUriRoot": "https://server.dcmjs.org//dcm4chee-arc/aets/DCM4CHEE/wado",
          "qidoRoot": "https://server.dcmjs.org/dcm4chee-arc/aets/DCM4CHEE/rs",
          "wadoRoot": "https://server.dcmjs.org/dcm4chee-arc/aets/DCM4CHEE/rs",
          "qidoSupportsIncludeField": true,
          "imageRendering": "wadors",
          "thumbnailRendering": "wadors",
          "requestOptions": {
            "requestFromBrowser": true,
            "logRequests": true,
            "logResponses": false,
            "logTiming": true
          }
        }
      ]
    }
  }
}
